db_pythonsdk/__init__.py
db_pythonsdk/filter_operators.py
db_pythonsdk/logical_operators.py
db_pythonsdk/operators.py
db_pythonsdk/query_i.py
db_pythonsdk/sdk.py
db_pythonsdk/sdk_i.py
db_pythonsdk/tests/__init__.py
db_pythonsdk/tests/filter_test.py
db_pythonsdk/tests/logical_test.py
db_pythonsdk/tests/sdk_test.py
db_pythonsdk-1.1.dist-info/METADATA
db_pythonsdk-1.1.dist-info/WHEEL
db_pythonsdk-1.1.dist-info/top_level.txt
db_pythonsdk-1.1.dist-info/RECORD
